endstech_shared/Settings.py
endstech_shared/__init__.py
endstech_shared/directory_utils.py
endstech_shared/endstech_json.py
endstech_shared/environment_utils.py
endstech_shared/languages.py
endstech_shared/logging_utils.py
endstech_shared/qt_chart_utils.py
endstech_shared/qt_combo_box_utils.py
endstech_shared/qt_translation_utils.py
endstech_shared/sqlalchemy_utils.py
endstech_shared-0.0.4.dist-info/LICENSE
endstech_shared-0.0.4.dist-info/METADATA
endstech_shared-0.0.4.dist-info/WHEEL
endstech_shared-0.0.4.dist-info/top_level.txt
endstech_shared-0.0.4.dist-info/RECORD
