Metadata-Version: 2.1
Name: endstech_shared
Version: 0.0.4
Summary: Shared code used by endstech
Home-page: https://github.com/jwaggy/endstech_shared
Author: Joseph Waggy
Author-email: jwaggy@gmail.com
Classifier: Development Status :: 4 - Beta
Classifier: Intended Audience :: Developers
Classifier: License :: OSI Approved :: GNU General Public License v3 (GPLv3)
Classifier: Natural Language :: English
Classifier: Operating System :: OS Independent
Classifier: Programming Language :: Python :: 3.9
Classifier: Programming Language :: Python :: 3.10
Classifier: Programming Language :: Python :: 3.11
Classifier: Topic :: Software Development
License-File: LICENSE
Requires-Dist: pyside6 >=6.7.2
Requires-Dist: SQLAlchemy >=2.0.31
Requires-Dist: alembic >=1.13.2
Requires-Dist: python-dateutil >=2.9.0
Requires-Dist: pytz >=2024.1
